sfcurves/__init__.py
sfcurves/hilbert.py
sfcurves/outline.py
sfcurves-1.0.0.dist-info/METADATA
sfcurves-1.0.0.dist-info/WHEEL
sfcurves-1.0.0.dist-info/top_level.txt
sfcurves-1.0.0.dist-info/RECORD
