Metadata-Version: 2.1
Name: sfcurves
Version: 1.0.0
Summary: utilities for space filling curves
Home-page: https://github.com/lwerdna/sfcurves
Author: Andrew Lamoureux
Author-email: foo@bar.com
License: UNKNOWN
Platform: UNKNOWN
Classifier: Programming Language :: Python :: 3
Classifier: License :: Public Domain
Classifier: Operating System :: OS Independent
